memori/__init__.py
memori/__main__.py
memori/_cli.py
memori/_config.py
memori/_exceptions.py
memori/_logging.py
memori/_network.py
memori/_search.py
memori/_setup.py
memori/_utils.py
memori/py.typed
memori/api/_quota.py
memori/api/_sign_up.py
memori/llm/__init__.py
memori/llm/_base.py
memori/llm/_clients.py
memori/llm/_constants.py
memori/llm/_embeddings.py
memori/llm/_invoke.py
memori/llm/_iterable.py
memori/llm/_iterator.py
memori/llm/_providers.py
memori/llm/_registry.py
memori/llm/_streaming.py
memori/llm/_utils.py
memori/llm/_xai_wrappers.py
memori/llm/adapters/anthropic/__init__.py
memori/llm/adapters/anthropic/_adapter.py
memori/llm/adapters/bedrock/__init__.py
memori/llm/adapters/bedrock/_adapter.py
memori/llm/adapters/google/__init__.py
memori/llm/adapters/google/_adapter.py
memori/llm/adapters/openai/__init__.py
memori/llm/adapters/openai/_adapter.py
memori/llm/adapters/xai/__init__.py
memori/llm/adapters/xai/_adapter.py
memori/memory/_collector.py
memori/memory/_manager.py
memori/memory/_struct.py
memori/memory/_writer.py
memori/memory/recall.py
memori/memory/augmentation/__init__.py
memori/memory/augmentation/_base.py
memori/memory/augmentation/_db_writer.py
memori/memory/augmentation/_manager.py
memori/memory/augmentation/_models.py
memori/memory/augmentation/_registry.py
memori/memory/augmentation/_runtime.py
memori/memory/augmentation/input.py
memori/memory/augmentation/augmentations/memori/__init__.py
memori/memory/augmentation/augmentations/memori/_augmentation.py
memori/memory/augmentation/memories/_conversation.py
memori/memory/augmentation/memories/_entity.py
memori/memory/augmentation/memories/_process.py
memori/storage/__init__.py
memori/storage/_base.py
memori/storage/_builder.py
memori/storage/_connection.py
memori/storage/_manager.py
memori/storage/_registry.py
memori/storage/adapters/dbapi/__init__.py
memori/storage/adapters/dbapi/_adapter.py
memori/storage/adapters/django/__init__.py
memori/storage/adapters/django/_adapter.py
memori-3.1.3.dist-info/licenses/LICENSE
memori-3.1.3.dist-info/METADATA
memori-3.1.3.dist-info/WHEEL
memori-3.1.3.dist-info/top_level.txt
memori-3.1.3.dist-info/RECORD
