Metadata-Version: 2.4
Name: memori
Version: 3.1.3
Summary: Memori Python SDK
Author-email: Memori Labs Team <noc@memorilabs.ai>
License: Apache-2.0
Project-URL: Homepage, https://memorilabs.ai
Project-URL: Documentation, https://memorilabs.ai/docs/
Project-URL: Repository, https://github.com/MemoriLabs/Memori
Project-URL: Bug Tracker, https://github.com/MemoriLabs/Memori/issues
Project-URL: Changelog, https://github.com/MemoriLabs/Memori/blob/main/CHANGELOG.md
Project-URL: Contributing, https://github.com/MemoriLabs/Memori/blob/main/CONTRIBUTING.md
Keywords: ai,memory,agents,llm,artificial-intelligence,multi-agent
Classifier: Development Status :: 3 - Alpha
Classifier: Intended Audience :: Developers
Classifier: License :: OSI Approved :: Apache Software License
Classifier: Operating System :: OS Independent
Classifier: Programming Language :: Python :: 3
Classifier: Programming Language :: Python :: 3.10
Classifier: Programming Language :: Python :: 3.11
Classifier: Programming Language :: Python :: 3.12
Classifier: Topic :: Scientific/Engineering :: Artificial Intelligence
Classifier: Topic :: Software Development :: Libraries :: Python Modules
Classifier: Topic :: Database :: Database Engines/Servers
Classifier: Typing :: Typed
Requires-Python: >=3.10
License-File: LICENSE
Requires-Dist: aiohttp>=3.9.0
Requires-Dist: botocore>=1.34.0
Requires-Dist: faiss-cpu>=1.7.0
Requires-Dist: grpcio>=1.60.0
Requires-Dist: numpy>=1.24.0
Requires-Dist: protobuf<6.0.0,>=4.25.0
Requires-Dist: psycopg[binary]>=3.1.0
Requires-Dist: pyfiglet>=0.8.0
Requires-Dist: requests>=2.32.5
Requires-Dist: sentence-transformers>=3.0.0
Dynamic: license-file
